{"meta": {"code": 200, "requestId": "5feddafbe2c947606ef28ad1"}, "response": {"headerLocation": "Clissold", "headerFullLocation": "Clissold, London", "headerLocationGranularity": "neighborhood", "query": "arts entertainment", "totalResults": 6, "suggestedBounds": {"ne": {"lat": 51.555730003600004, "lng": -0.07534118283642362}, "sw": {"lat": 51.54852999639999, "lng": -0.08689881716357638}}, "groups": [{"type": "Recommended Places", "name": "recommended", "items": [{"reasons": {"count": 0, "items": [{"summary": "This spot is popular", "type": "general", "reasonName": "globalInteractionReason"}]}, "venue": {"id": "4f4ff4a2e4b01fd34e8461b4", "name": "Space Fiftyfour", "location": {"address": "54 Rivington St", "lat": 51.553632116910116, "lng": -0.08028065540549874, "labeledLatLngs": [{"label": "display", "lat": 51.553632116910116, "lng": -0.08028065540549874}], "distance": 177, "postalCode": "Ec2a 3qn", "cc": "GB", "city": "London", "state": "Greater London", "country": "United Kingdom", "formattedAddress": ["54 Rivington St", "London", "Greater London", "Ec2a 3qn", "United Kingdom"]}, "categories": [{"id": "4bf58dd8d48988d1e2931735", "name": "Art Gallery", "pluralName": "Art Galleries", "shortName": "Art Gallery", "icon": {"prefix": "https://ss3.4sqi.net/img/categories_v2/arts_entertainment/artgallery_", "suffix": ".png"}, "primary": true}], "photos": {"count": 0, "groups": []}}, "referralId": "e-0-4f4ff4a2e4b01fd34e8461b4-0"}, {"reasons": {"count": 0, "items": [{"summary": "This spot is popular", "type": "general", "reasonName": "globalInteractionReason"}]}, "venue": {"id": "51c5b98c498e54799fa6c196", "name": "13thegallery", "location": {"lat": 51.552465, "lng": -0.085989, "labeledLatLngs": [{"label": "display", "lat": 51.552465, "lng": -0.085989}], "distance": 339, "cc": "GB", "city": "London", "state": "Greater London", "country": "United Kingdom", "formattedAddress": ["London", "Greater London", "United Kingdom"]}, "categories": [{"id": "4bf58dd8d48988d1e2931735", "name": "Art Gallery", "pluralName": "Art Galleries", "shortName": "Art Gallery", "icon": {"prefix": "https://ss3.4sqi.net/img/categories_v2/arts_entertainment/artgallery_", "suffix": ".png"}, "primary": true}], "photos": {"count": 0, "groups": []}}, "referralId": "e-0-51c5b98c498e54799fa6c196-1"}, {"reasons": {"count": 0, "items": [{"summary": "This spot is popular", "type": "general", "reasonName": "globalInteractionReason"}]}, "venue": {"id": "5742ca6e498e3e12b175adc1", "name": "Pocko", "location": {"lat": 51.549389, "lng": -0.078765, "labeledLatLngs": [{"label": "display", "lat": 51.549389, "lng": -0.078765}], "distance": 345, "postalCode": "N1", "cc": "GB", "city": "London", "state": "Greater London", "country": "United Kingdom", "formattedAddress": ["London", "Greater London", "N1", "United Kingdom"]}, "categories": [{"id": "4bf58dd8d48988d1e2931735", "name": "Art Gallery", "pluralName": "Art Galleries", "shortName": "Art Gallery", "icon": {"prefix": "https://ss3.4sqi.net/img/categories_v2/arts_entertainment/artgallery_", "suffix": ".png"}, "primary": true}], "photos": {"count": 0, "groups": []}}, "referralId": "e-0-5742ca6e498e3e12b175adc1-2"}, {"reasons": {"count": 0, "items": [{"summary": "This spot is popular", "type": "general", "reasonName": "globalInteractionReason"}]}, "venue": {"id": "52ecd195498e4960c8b0d37d", "name": "13 The Gallery", "location": {"lat": 51.552307829985274, "lng": -0.08633223406751571, "labeledLatLngs": [{"label": "display", "lat": 51.552307829985274, "lng": -0.08633223406751571}], "distance": 361, "cc": "GB", "country": "United Kingdom", "formattedAddress": ["United Kingdom"]}, "categories": [{"id": "4bf58dd8d48988d1e2931735", "name": "Art Gallery", "pluralName": "Art Galleries", "shortName": "Art Gallery", "icon": {"prefix": "https://ss3.4sqi.net/img/categories_v2/arts_entertainment/artgallery_", "suffix": ".png"}, "primary": true}], "photos": {"count": 0, "groups": []}}, "referralId": "e-0-52ecd195498e4960c8b0d37d-3"}, {"reasons": {"count": 0, "items": [{"summary": "This spot is popular", "type": "general", "reasonName": "globalInteractionReason"}]}, "venue": {"id": "5742ca95498eddde810877d1", "name": "Pocko", "location": {"lat": 51.549277, "lng": -0.078096, "labeledLatLngs": [{"label": "display", "lat": 51.549277, "lng": -0.078096}], "distance": 380, "cc": "GB", "country": "United Kingdom", "formattedAddress": ["United Kingdom"]}, "categories": [{"id": "4bf58dd8d48988d1e2931735", "name": "Art Gallery", "pluralName": "Art Galleries", "shortName": "Art Gallery", "icon": {"prefix": "https://ss3.4sqi.net/img/categories_v2/arts_entertainment/artgallery_", "suffix": ".png"}, "primary": true}], "photos": {"count": 0, "groups": []}}, "referralId": "e-0-5742ca95498eddde810877d1-4"}, {"reasons": {"count": 0, "items": [{"summary": "This spot is popular", "type": "general", "reasonName": "globalInteractionReason"}]}, "venue": {"id": "54ce9847498ed053564a01e3", "name": "Gramafon", "location": {"address": "19 Green Lanes", "crossStreet": "Newington Green", "lat": 51.55284689798807, "lng": -0.08663736841953003, "labeledLatLngs": [{"label": "display", "lat": 51.55284689798807, "lng": -0.08663736841953003}], "distance": 390, "postalCode": "N16 9BS", "cc": "GB", "city": "London", "state": "Greater London", "country": "United Kingdom", "formattedAddress": ["19 Green Lanes (Newington Green)", "London", "Greater London", "N16 9BS", "United Kingdom"]}, "categories": [{"id": "4bf58dd8d48988d1e5931735", "name": "Music Venue", "pluralName": "Music Venues", "shortName": "Music Venue", "icon": {"prefix": "https://ss3.4sqi.net/img/categories_v2/arts_entertainment/musicvenue_", "suffix": ".png"}, "primary": true}], "photos": {"count": 0, "groups": []}}, "referralId": "e-0-54ce9847498ed053564a01e3-5"}]}]}}