{"meta": {"code": 200, "requestId": "5feddcdb8028c13d493eab0d"}, "response": {"warning": {"text": "There aren't a lot of results near you. Try something more general, reset your filters, or expand the search area."}, "headerLocation": "Romford Town", "headerFullLocation": "Romford Town, London", "headerLocationGranularity": "neighborhood", "query": "arts entertainment", "totalResults": 1, "suggestedBounds": {"ne": {"lat": 51.57784000360001, "lng": 0.17876162769719514}, "sw": {"lat": 51.5706399964, "lng": 0.16719837230280485}}, "groups": [{"type": "Recommended Places", "name": "recommended", "items": [{"reasons": {"count": 0, "items": [{"summary": "This spot is popular", "type": "general", "reasonName": "globalInteractionReason"}]}, "venue": {"id": "54855576498ebe470bb17b28", "name": "Romford Folk Club", "location": {"lat": 51.5750801, "lng": 0.1754417, "labeledLatLngs": [{"label": "display", "lat": 51.5750801, "lng": 0.1754417}], "distance": 194, "cc": "GB", "city": "Romford", "state": "Greater London", "country": "United Kingdom", "formattedAddress": ["Romford", "Greater London", "United Kingdom"]}, "categories": [{"id": "4bf58dd8d48988d1f2931735", "name": "Performing Arts Venue", "pluralName": "Performing Arts Venues", "shortName": "Performing Arts", "icon": {"prefix": "https://ss3.4sqi.net/img/categories_v2/arts_entertainment/performingarts_", "suffix": ".png"}, "primary": true}], "photos": {"count": 0, "groups": []}}, "referralId": "e-0-54855576498ebe470bb17b28-0"}]}]}}